tree_sitter_follow/__init__.py
tree_sitter_follow/__init__.pyi
tree_sitter_follow/_binding.pyd
tree_sitter_follow/binding.c
tree_sitter_follow/py.typed
tree_sitter_follow-0.1.0.dist-info/METADATA
tree_sitter_follow-0.1.0.dist-info/WHEEL
tree_sitter_follow-0.1.0.dist-info/top_level.txt
tree_sitter_follow-0.1.0.dist-info/RECORD
